{
  "button.details": "详情",
  "button.close": "关闭",
  "button.copyReport": "复制报告",
  "panel.title": "加入失败详情",
  "section.summary": "概要",
  "column.item": "项目",
  "column.host": "主机",
  "column.local": "本地",
  "column.hostOrder": "主机顺序",
  "column.localOrder": "本地顺序",
  "snapshot.version": "版本：{0}",
  "snapshot.modelDb": "ModelDb：{0}",
  "snapshot.modelDbMode": "ModelDb 模式：{0}",
  "snapshot.mods": "影响玩法 Mod：{0}",
  "footer.networkReason": "网络原因：{0}",
  "footer.networkInfo": "信息：{0}",
  "issue.transport.title": "未收到游戏信息握手",
  "issue.transport.body": "连接在主机发送游戏信息前失败。网络原因：{0}。",
  "issue.hostRejected.title": "主机拒绝加入",
  "issue.hostRejected.body": "主机明确拒绝了加入请求：{0}。",
  "issue.version.title": "游戏版本不匹配",
  "issue.version.body": "主机与本地游戏版本不同。",
  "issue.modSet.title": "影响玩法 Mod 不匹配",
  "issue.modSet.body": "主机与本地的影响玩法 Mod 列表不同。",
  "issue.modOrder.title": "影响玩法 Mod 顺序不同",
  "issue.modOrder.body": "双方有相同的影响玩法 Mod，但加载顺序不同。",
  "issue.modOrder.body.deterministic": "双方有相同的影响玩法 Mod，但加载顺序不同。双方的 ModelDb 哈希都基于确定性最终内容生成，因此仅顺序不同不应改变它。",
  "issue.modOrder.body.existing": "双方有相同的影响玩法 Mod，但加载顺序不同。至少一方未启用确定性最终内容哈希，因此加载顺序仍可能通过既有初始化路径影响诊断。",
  "issue.modelDbHashMode.title": "ModelDb 哈希模式不同",
  "issue.modelDbHashMode.body": "一端报告了 ModelDb 稳定排序，另一端没有报告。另一端可能未启用该设置、缺少该能力，或正在使用较旧的 RitsuLib 版本。",
  "issue.modelDb.title": "ModelDb 哈希不匹配",
  "issue.modelDb.body": "主机与本地的玩法模型数据库不同。",
  "issue.modelDb.body.deterministic": "主机与本地的玩法模型数据库不同，即使双方都使用了确定性 ModelDb 哈希。如果 Mod 列表一致，请检查运行时模型注册、直接 ModelDb patch 或本地 Mod 文件差异。",
  "issue.modelDb.body.existing": "主机与本地的玩法模型数据库不同。至少一方未启用确定性最终内容哈希，因此也需要比较 Mod 加载顺序，以及其他库、patch 或运行时注册差异。",
  "issue.modelDb.body.modeMismatch": "主机与本地的玩法模型数据库不同，并且只有一端报告了 ModelDb 稳定排序。请让双方启用相同的 ModelDb 确定性排序设置，并使用支持报告该模式的 RitsuLib 版本。",
  "issue.network.title": "网络失败",
  "issue.network.body": "加入失败，网络原因：{0}。",
  "row.gameVersion": "游戏版本",
  "row.modelDbHash": "ModelDb 哈希",
  "row.modelDbHashMode": "ModelDb 哈希模式",
  "row.more": "另有 {0} 项",
  "row.orderMismatchCount": "不同位置数量",
  "row.firstDifferentPosition": "首个不同位置：{0}",
  "value.missing": "缺失",
  "value.noVersion": "无版本",
  "value.omitted": "已省略",
  "value.same": "相同",
  "value.differs": "不同",
  "value.modelDbHashMode.deterministic": "稳定排序",
  "value.modelDbHashMode.notReported": "未报告稳定排序",
  "toast.reportCopied.title": "加入诊断",
  "toast.reportCopied.body": "加入失败报告已复制到剪贴板。",
  "reason.None": "无",
  "reason.Quit": "退出",
  "reason.QuitGameOver": "游戏结束后退出",
  "reason.HostAbandoned": "主机放弃了跑局",
  "reason.Kicked": "被主机踢出",
  "reason.InvalidJoin": "无效加入",
  "reason.CancelledJoin": "加入已取消",
  "reason.LobbyFull": "房间已满",
  "reason.RunInProgress": "跑局已经开始",
  "reason.NotInSaveGame": "不在存档跑局中",
  "reason.VersionMismatch": "版本或 ModelDb 不匹配",
  "reason.JoinBlockedByUser": "加入被用户阻止",
  "reason.StateDivergence": "状态分歧",
  "reason.HandshakeTimeout": "握手超时",
  "reason.ModMismatch": "Mod 不匹配",
  "reason.NoInternet": "无网络连接",
  "reason.Timeout": "连接超时",
  "reason.InternalError": "内部错误",
  "reason.UnknownNetworkError": "未知网络错误",
  "reason.RateLimited": "请求过于频繁",
  "reason.TryAgainLater": "请稍后重试",
  "reason.FailedToHost": "创建房间失败",
  "reason.SecureConnectionFailed": "安全连接失败",
  "connection.None": "无",
  "connection.LobbyFull": "房间已满",
  "connection.NotInSaveGame": "加入者不在该存档跑局中",
  "connection.RunInProgress": "跑局已经开始",
  "connection.VersionMismatch": "版本不匹配",
  "connection.ModMismatch": "Mod 不匹配"
}
